digikala_bi_utils/__init__.py
digikala_bi_utils/utils.py
digikala_bi_utils-0.0.1.dist-info/METADATA
digikala_bi_utils-0.0.1.dist-info/WHEEL
digikala_bi_utils-0.0.1.dist-info/licenses/LICENSE
digikala_bi_utils-0.0.1.dist-info/RECORD
